LICENSE.rst
MANIFEST.in
README.rst
setup.py
fullcontacter/__init__.py
fullcontacter/fullcontacter.py
fullcontacter/lookup.py
fullcontacter.egg-info/PKG-INFO
fullcontacter.egg-info/SOURCES.txt
fullcontacter.egg-info/dependency_links.txt
fullcontacter.egg-info/not-zip-safe
fullcontacter.egg-info/requires.txt
fullcontacter.egg-info/top_level.txt