Metadata-Version: 1.1
Name: fullcontacter
Version: 0.3.1
Summary: Library for interacting with Fullcontact's APIs.
Home-page: http://github.com/patrick-russell/fullcontacter
Author: Patrick Russell
Author-email: prussell@gmail.com
License: MIT
Keywords: contact information fullcontact
Platform: UNKNOWN
Classifier: Development Status :: 2 - Pre-Alpha
Classifier: License :: OSI Approved :: MIT License
Classifier: Programming Language :: Python :: 2.7
